{
  "title": "Memdot Service Health",
  "uid": "memdot-service-health",
  "schemaVersion": 39,
  "version": 2,
  "tags": ["memdot", "ops", "content-free"],
  "timezone": "browser",
  "time": { "from": "now-1h", "to": "now" },
  "panels": [
    {
      "id": 1,
      "type": "stat",
      "title": "Service up samples",
      "gridPos": { "h": 4, "w": 6, "x": 0, "y": 0 },
      "targets": [
        {
          "refId": "A",
          "expr": "up",
          "legendFormat": "{{job}}"
        }
      ],
      "fieldConfig": {
        "defaults": {
          "unit": "none",
          "mappings": []
        }
      }
    },
    {
      "id": 2,
      "type": "timeseries",
      "title": "Request failure rate",
      "gridPos": { "h": 8, "w": 12, "x": 6, "y": 0 },
      "targets": [
        {
          "refId": "A",
          "expr": "sum(rate(http_server_request_duration_seconds_count{http_response_status_code=~\"5..\"}[5m])) or vector(0)",
          "legendFormat": "5xx"
        }
      ]
    },
    {
      "id": 3,
      "type": "stat",
      "title": "Dependency readiness",
      "gridPos": { "h": 4, "w": 6, "x": 0, "y": 4 },
      "targets": [
        {
          "refId": "A",
          "expr": "count(up == 1) or vector(0)"
        }
      ]
    }
  ]
}
